doces_core.cpython-39-x86_64-linux-gnu.so
doces-0.0.9.dist-info/WHEEL
doces-0.0.9.dist-info/RECORD
doces-0.0.9.dist-info/top_level.txt
doces-0.0.9.dist-info/METADATA
doces-0.0.9.dist-info/licenses/LICENSE
doces/doces.py
doces/__init__.py
