Metadata-Version: 2.1
Name: doces
Version: 0.0.9
Summary: DOCES is an experimental library to simulate opinion dynamics on complex networks
Home-page: https://github.com/hfarruda/doces
Author: Henrique F. de Arruda, Kleber A. Oliveira, and Yamir Moreno
Author-email: h.f.arruda@gmail.com
Classifier: Programming Language :: Python :: 3
Classifier: License :: OSI Approved :: MIT License
Classifier: Operating System :: MacOS :: MacOS X
Classifier: Operating System :: Microsoft :: Windows
Classifier: Operating System :: POSIX :: Linux
Classifier: Development Status :: 3 - Alpha
Classifier: Programming Language :: C
Classifier: Topic :: Scientific/Engineering :: Physics
Classifier: Intended Audience :: Science/Research
Requires-Python: >=3.6
License-File: LICENSE
Requires-Dist: numpy <2.0
